battle_test/__init__.py
battle_test/main.py
battle_test-0.0.3.dist-info/METADATA
battle_test-0.0.3.dist-info/WHEEL
battle_test-0.0.3.dist-info/top_level.txt
battle_test-0.0.3.dist-info/RECORD
