Metadata-Version: 2.1
Name: battle-test
Version: 0.0.3
Summary: A airtest package for battle test.
Home-page: https://github.com/virtualeconomy/pyvsystems
Author: bingo
License: MIT
Keywords: battletest
Platform: UNKNOWN
Requires-Dist: airtest (>=1.1.11)
